MANIFEST.in
NEWS
README
setup.py
./__init__.py
./_mapper.py
./cover.py
./cutoff.py
./draw_mapper_output.py
./filters.py
./mapper_output.py
./metric.py
./scale_graph.py
./shapes.py
./d3js/d3jsexample.html
./d3js/mapper.json
./exampleshapes/README.txt
./exampleshapes/camel-reference.csv.gz
./exampleshapes/cat-reference.csv.gz
./exampleshapes/elephant-reference.csv.gz
./exampleshapes/face-reference.csv.gz
./exampleshapes/flam-reference.csv.gz
./exampleshapes/head-reference.csv.gz
./exampleshapes/horse-reference.csv.gz
./exampleshapes/lion-reference.csv.gz
./tools/__init__.py
./tools/graphviz_interface.py
./tools/pdfwriter.py
./tools/progressreporter.py
./tools/quickhull2d.py
./tools/shortest_path.py
bin/MapperGUI.py
doc/Makefile
doc/make.bat
doc/source/GUI_screenshot.png
doc/source/GUI_screenshot_single.png
doc/source/Mapper_output_screenshot_1.png
doc/source/Mapper_output_screenshot_2.png
doc/source/Mapper_output_screenshot_3.png
doc/source/Mapper_output_screenshot_3a.png
doc/source/Mapper_output_screenshot_3b.png
doc/source/Mapper_output_screenshot_3c.png
doc/source/Mapper_output_screenshot_4.png
doc/source/Mapper_output_screenshot_5.png
doc/source/Screenshot.png
doc/source/conf.py
doc/source/cover.rst
doc/source/figure_navigation.rst
doc/source/filters.rst
doc/source/index.rst
doc/source/input.rst
doc/source/introduction.rst
doc/source/jet.png
doc/source/legal.rst
doc/source/mapper.rst
doc/source/mapperoutputwindow.rst
doc/source/node_coloring.rst
doc/source/ownpythoncode.rst
doc/source/quickstart.rst
doc/source/_static/mapper.png
doc/source/inputfields/filter.png
doc/source/inputfields/filter0.png
doc/source/inputfields/imagemagick.txt
doc/source/inputfields/node_coloring.png
doc/source/inputfields/node_coloring0.png
doc/source/inputfields/preprocessing.png
doc/source/inputfields/preprocessing0.png
doc/source/installation/index.rst
doc/source/installation/installation_tips_arch.rst
doc/source/installation/installation_tips_osx.rst
mapper.egg-info/PKG-INFO
mapper.egg-info/SOURCES.txt
mapper.egg-info/dependency_links.txt
mapper.egg-info/top_level.txt